CHANGELOG.rst
openldap_schema_parser/__init__.py
openldap_schema_parser/attribute.py
openldap_schema_parser/command.py
openldap_schema_parser/exceptions.py
openldap_schema_parser/objectclass.py
openldap_schema_parser/objectidentifier.py
openldap_schema_parser/parser.py
openldap_schema_parser/py.typed
openldap_schema_parser/schema.lark
openldap_schema_parser/schema.py
openldap_schema_parser/schema_parser.py
openldap_schema_parser-1.1.11.dist-info/LICENSE
openldap_schema_parser-1.1.11.dist-info/METADATA
openldap_schema_parser-1.1.11.dist-info/WHEEL
openldap_schema_parser-1.1.11.dist-info/entry_points.txt
openldap_schema_parser-1.1.11.dist-info/RECORD
