Metadata-Version: 2.1
Name: openldap-schema-parser
Version: 1.1.11
Summary: OpenLDAP schema file parser
Home-page: https://github.com/mypaceshun/openldap-schema-parser
License: MIT
Keywords: OpenLDAP,schema,parser
Author: KAWAI Shun
Author-email: shun@osstech.co.jp
Requires-Python: >=3.8,<4.0
Classifier: License :: OSI Approved :: MIT License
Classifier: Programming Language :: Python :: 3
Classifier: Programming Language :: Python :: 3.8
Classifier: Programming Language :: Python :: 3.9
Classifier: Programming Language :: Python :: 3.10
Classifier: Programming Language :: Python :: 3.11
Requires-Dist: click (>=8.1.2,<9.0.0)
Requires-Dist: rich (>=12.2.0,<13.0.0)
Project-URL: Documentation, https://openldap-schema-parser.readthedocs.io/
Project-URL: Repository, https://github.com/mypaceshun/openldap-schema-parser
